odoo/addons/base_name_search_multi_lang/README.rst
odoo/addons/base_name_search_multi_lang/__init__.py
odoo/addons/base_name_search_multi_lang/__manifest__.py
odoo/addons/base_name_search_multi_lang/i18n/base_name_search_multi_lang.pot
odoo/addons/base_name_search_multi_lang/models/__init__.py
odoo/addons/base_name_search_multi_lang/models/ir_model.py
odoo/addons/base_name_search_multi_lang/readme/CONFIGURE.rst
odoo/addons/base_name_search_multi_lang/readme/CONTRIBUTORS.rst
odoo/addons/base_name_search_multi_lang/readme/DESCRIPTION.rst
odoo/addons/base_name_search_multi_lang/readme/USAGE.rst
odoo/addons/base_name_search_multi_lang/static/description/icon.png
odoo/addons/base_name_search_multi_lang/static/description/index.html
odoo/addons/base_name_search_multi_lang/tests/__init__.py
odoo/addons/base_name_search_multi_lang/tests/test_name_search.py
odoo/addons/base_name_search_multi_lang/views/ir_model_views.xml
odoo13_addon_base_name_search_multi_lang-13.0.1.0.1.dist-info/METADATA
odoo13_addon_base_name_search_multi_lang-13.0.1.0.1.dist-info/WHEEL
odoo13_addon_base_name_search_multi_lang-13.0.1.0.1.dist-info/top_level.txt
odoo13_addon_base_name_search_multi_lang-13.0.1.0.1.dist-info/RECORD
